{"meta": {"timestamp": "2024-02-27T01:52:47.076093", "version": "7.0.1", "argv": ["-r", "/opt/capa-rules-7.0.1/", "-j", "/tmp/KBDTIPRD.DLL"], "sample": {"md5": "20d88cf75ab0f50506782b2b09e4081e", "sha1": "e1107facaeedb0aac14cd6ee1ab625aa5d2b1314", "sha256": "fd7854f7f6a54c2373da681d578abee63a230212920614e6766d5406d48f0c59", "path": "/tmp/KBDTIPRD.DLL"}, "flavor": "static", "analysis": {"format": "pe", "arch": "amd64", "os": "windows", "extractor": "VivisectFeatureExtractor", "rules": ["/opt/capa-rules-7.0.1"], "base_address": {"type": "absolute", "value": 6442450944}, "layout": {"functions": []}, "feature_counts": {"file": 111, "functions": [{"address": {"type": "absolute", "value": 6442455056}, "count": 9}]}, "library_functions": []}}, "rules": {}}